[
    { "maSP": 1, "tenSP": "VinSmart Live", "manHinh": "AMOLED, 6.2, Full HD+", "heDieuHanh": "Android 9.0 (Pie)", "cameraTruoc": "20 MP", "cameraSau": "Chính 48 MP & Phụ 8 MP, 5 MP", "ram": "4 GB", "rom": "64 GB", "giaBan": 5700000, "hinhAnh": "./img/vsphone.jpg", "soluong":"1" },
    { "maSP": 2, "tenSP": "Meizu 16Xs", "manHinh": "AMOLED, FHD+ 2232 x 1080 pixels", "heDieuHanh": "Android 9.0 (Pie); Flyme", "cameraTruoc": "20 MP", "cameraSau": "Chính 48 MP & Phụ 8 MP, 5 MP", "ram": "4 GB", "rom": "64 GB", "giaBan": 7600000, "hinhAnh": "./img/meizuphone.jpg", "soluong":"1" },
    { "maSP": 3, "tenSP": "Iphone XS Max", "manHinh": "OLED, 6.5, 1242 x 2688 Pixels", "heDieuHanh": "iOS 12", "cameraSau": "Chính 12 MP & Phụ 12 MP", "cameraTruoc": "7 MP", "ram": "4 GB", "rom": "64 GB", "giaBan": 27000000, "hinhAnh": "./img/applephone.jpg", "soluong":"1" },
    { "maSP": 4, "tenSP": "Galaxy-S22", "manHinh": "Dynamic AMOLED 2X6.8 Quad HD+ (2K+)", "heDieuHanh": "Android 12", "cameraSau": "Chính 108 MP & Phụ 12 MP, 10 MP, 10 MP", "cameraTruoc": "40 MP", "ram": "8 GB", "rom": "128 GB", "giaBan": 27990000, "hinhAnh": "./img/Galaxy-S22-Ultra-Burgundy-600x600.jpg", "soluong":"1"},
    { "maSP": 5, "tenSP": "Iphone 11", "manHinh": "IPS LCD 6.1 Liquid Retina", "heDieuHanh": "iOS 15", "cameraSau": "2 camera 12 MP", "cameraTruoc": "12 MP", "ram": "8 GB", "rom": "128 GB", "giaBan": 12200000, "hinhAnh": "./img/iphone.jpg", "soluong":"1"},
    { "maSP": 6, "tenSP": "Oppo reno7", "manHinh": "IPS LCD 6.1 Liquid Retina", "heDieuHanh": "iOS 15", "cameraSau": "2 camera 12 MP", "cameraTruoc": "12 MP", "ram": "8 GB", "rom": "128 GB", "giaBan": 12200000, "hinhAnh": "./img/oppo-reno7.jpg", "soluong":"1"},
    { "maSP": 7, "tenSP": "RealmeC35", "manHinh": "IPS LCD 6.1 Liquid Retina", "heDieuHanh": "iOS 15", "cameraSau": "2 camera 12 MP", "cameraTruoc": "12 MP", "ram": "8 GB", "rom": "128 GB", "giaBan": 12200000, "hinhAnh": "./img/realme.jpg", "soluong":"1"},
    { "maSP": 8, "tenSP": "Xiaomi Redmi Note 11", "manHinh": "IPS LCD 6.1 Liquid Retina", "heDieuHanh": "iOS 15", "cameraSau": "2 camera 12 MP", "cameraTruoc": "12 MP", "ram": "8 GB", "rom": "128 GB", "giaBan": 12200000, "hinhAnh": "./img/xiaomi-redmi-note-11.jpg", "soluong":"1"}
]